astrometry_azel/__init__.py
astrometry_azel/imgAvgStack.py
astrometry_azel/io.py
astrometry_azel/plots.py
astrometry_azel-1.2.0.data/scripts/PlateScale.py
astrometry_azel-1.2.0.data/scripts/PlateScaleFITS.py
astrometry_azel-1.2.0.data/scripts/PrintSourceRaDec.py
astrometry_azel-1.2.0.data/scripts/downloadIndex.py
astrometry_azel-1.2.0.dist-info/DESCRIPTION.rst
astrometry_azel-1.2.0.dist-info/METADATA
astrometry_azel-1.2.0.dist-info/RECORD
astrometry_azel-1.2.0.dist-info/WHEEL
astrometry_azel-1.2.0.dist-info/metadata.json
astrometry_azel-1.2.0.dist-info/top_level.txt
