Metadata-Version: 2.0
Name: astrometry-azel
Version: 1.2.0
Summary: Register images to az/el using the astrometry.net program
Home-page: https://github.com/scivision/astrometry_azel
Author: Michael Hirsch, Ph.D.
Author-email: UNKNOWN
License: UNKNOWN
Platform: UNKNOWN
Classifier: Development Status :: 5 - Production/Stable
Classifier: Environment :: Console
Classifier: Intended Audience :: Science/Research
Classifier: License :: OSI Approved :: MIT License
Classifier: Operating System :: OS Independent
Classifier: Programming Language :: Python :: 3
Classifier: Topic :: Scientific/Engineering :: Atmospheric Science
Requires-Python: >=3.6
Requires-Dist: astropy
Requires-Dist: numpy
Requires-Dist: pymap3d
Requires-Dist: python-dateutil
Requires-Dist: pytz
Requires-Dist: scipy
Requires-Dist: xarray
Provides-Extra: io
Requires-Dist: h5py; extra == 'io'
Requires-Dist: imageio; extra == 'io'
Requires-Dist: netcdf4; extra == 'io'
Provides-Extra: plot
Requires-Dist: matplotlib; extra == 'plot'
Requires-Dist: seaborn; extra == 'plot'
Provides-Extra: tests
Requires-Dist: coveralls; extra == 'tests'
Requires-Dist: nose; extra == 'tests'
Requires-Dist: pytest; extra == 'tests'
